fastpip/LICENSE
fastpip/__init__.py
fastpip/__version__.py
fastpip/com/__init__.py
fastpip/com/common.py
fastpip/core/__init__.py
fastpip/core/fastpip.py
fastpip/utils/__init__.py
fastpip/utils/cmdutil.py
fastpip/utils/findpath.py
fastpip-1.7.0.dist-info/LICENSE
fastpip-1.7.0.dist-info/METADATA
fastpip-1.7.0.dist-info/WHEEL
fastpip-1.7.0.dist-info/top_level.txt
fastpip-1.7.0.dist-info/RECORD
