Metadata-Version: 2.1
Name: fastpip
Version: 1.7.0
Summary: 一个 pip 命令包，帮助你实现使用 Python 编程的方式进行包管理操作。
Home-page: https://github.com/hrpzcf/fastpip
Author: hrpzcf
License: MIT License
Keywords: pip,package
Platform: win32
Platform: win_amd64
Classifier: Intended Audience :: Developers
Classifier: Development Status :: 4 - Beta
Classifier: License :: OSI Approved :: MIT License
Classifier: Programming Language :: Python :: 3.7
Classifier: Programming Language :: Python :: 3.8
Classifier: Programming Language :: Python :: 3.9
Classifier: Programming Language :: Python :: 3.10
Requires-Python: >=3.7
License-File: LICENSE
Requires-Dist: psutil (>=5.7.2)
Requires-Dist: chardet (>=4.0.0)
